nbgrader/__init__.py
nbgrader/__main__.py
nbgrader/_version.py
nbgrader/alembic.ini
nbgrader/api.py
nbgrader/coursedir.py
nbgrader/dbutil.py
nbgrader/utils.py
nbgrader/validator.py
nbgrader/alembic/env.py
nbgrader/alembic/script.py.mako
nbgrader/alembic/versions/167914646830_added_task_cells.py
nbgrader/alembic/versions/282d30a0218e_adds_lms_user_id_column_to_student_table.py
nbgrader/alembic/versions/50a4d84c131a_add_kernelspecs.py
nbgrader/alembic/versions/724cde206c17_add_extra_credit_column.py
nbgrader/alembic/versions/b6d005d67074_initial_alembic_revision.py
nbgrader/alembic/versions/e43177bfe90b_added_course_table_and_relationships.py
nbgrader/apps/__init__.py
nbgrader/apps/api.py
nbgrader/apps/assignapp.py
nbgrader/apps/autogradeapp.py
nbgrader/apps/baseapp.py
nbgrader/apps/collectapp.py
nbgrader/apps/dbapp.py
nbgrader/apps/exportapp.py
nbgrader/apps/extensionapp.py
nbgrader/apps/feedbackapp.py
nbgrader/apps/fetchapp.py
nbgrader/apps/fetchassignmentapp.py
nbgrader/apps/fetchfeedbackapp.py
nbgrader/apps/formgradeapp.py
nbgrader/apps/generateassignmentapp.py
nbgrader/apps/generateconfigapp.py
nbgrader/apps/generatefeedbackapp.py
nbgrader/apps/generatesolutionapp.py
nbgrader/apps/listapp.py
nbgrader/apps/nbgraderapp.py
nbgrader/apps/quickstartapp.py
nbgrader/apps/releaseapp.py
nbgrader/apps/releaseassignmentapp.py
nbgrader/apps/releasefeedbackapp.py
nbgrader/apps/submitapp.py
nbgrader/apps/updateapp.py
nbgrader/apps/validateapp.py
nbgrader/apps/zipcollectapp.py
nbgrader/auth/__init__.py
nbgrader/auth/base.py
nbgrader/auth/jupyterhub.py
nbgrader/converters/__init__.py
nbgrader/converters/assign.py
nbgrader/converters/autograde.py
nbgrader/converters/base.py
nbgrader/converters/feedback.py
nbgrader/converters/generate_assignment.py
nbgrader/converters/generate_feedback.py
nbgrader/converters/generate_solution.py
nbgrader/converters/generate_source_with_tests.py
nbgrader/docs/Makefile
nbgrader/docs/make.bat
nbgrader/docs/source/build_docs.py
nbgrader-0.9.5.dist-info/METADATA
nbgrader-0.9.5.dist-info/WHEEL
nbgrader-0.9.5.dist-info/entry_points.txt
nbgrader-0.9.5.dist-info/licenses/LICENSE
nbgrader-0.9.5.dist-info/RECORD
