Metadata-Version: 2.4
Name: nbgrader
Version: 0.9.5
Summary: A system for assigning and grading notebooks
Project-URL: Homepage, https://github.com/jupyter/nbgrader
Author-email: Jupyter Development Team <jupyter@googlegroups.com>
License: Copyright (c) 2014 Project Jupyter Contributors
License-File: LICENSE
Keywords: Grading,Homework,Jupyter,JupyterLab,Notebooks
Classifier: Framework :: Jupyter
Classifier: Framework :: Jupyter :: JupyterLab
Classifier: Framework :: Jupyter :: JupyterLab :: 4
Classifier: Framework :: Jupyter :: JupyterLab :: Extensions
Classifier: Framework :: Jupyter :: JupyterLab :: Extensions :: Prebuilt
Classifier: License :: OSI Approved :: BSD License
Classifier: Programming Language :: Python
Classifier: Programming Language :: Python :: 3
Requires-Python: >=3.8
Requires-Dist: alembic>=1.7
Requires-Dist: ipython>=8.10.0
Requires-Dist: ipywidgets>=7.6
Requires-Dist: jinja2>=3
Requires-Dist: jsonschema>=3
Requires-Dist: jupyter-client<9
Requires-Dist: jupyter-server>=2
Requires-Dist: jupyterlab-server
Requires-Dist: jupyterlab<5,>=4.2.0
Requires-Dist: nbclient>=0.6.1
Requires-Dist: nbconvert>=6
Requires-Dist: notebook<8,>=7.2.0
Requires-Dist: python-dateutil>=2.8
Requires-Dist: pyyaml>=6.0
Requires-Dist: rapidfuzz>=1.8
Requires-Dist: requests>=2.26
Requires-Dist: setuptools
Requires-Dist: sqlalchemy<3,>=1.4
Provides-Extra: dev
Requires-Dist: tbump; extra == 'dev'
Requires-Dist: toml; extra == 'dev'
Provides-Extra: docs
Requires-Dist: myst-parser; extra == 'docs'
Requires-Dist: sphinx-autodoc-typehints; extra == 'docs'
Requires-Dist: sphinx-rtd-theme>=1.3; extra == 'docs'
Requires-Dist: sphinx<8,>=7; extra == 'docs'
Provides-Extra: tests
Requires-Dist: codecov; extra == 'tests'
Requires-Dist: coverage; extra == 'tests'
Requires-Dist: jupyter-packaging; extra == 'tests'
Requires-Dist: nbval>=0.11.0; extra == 'tests'
Requires-Dist: pytest-cov; extra == 'tests'
Requires-Dist: pytest-jupyter; extra == 'tests'
Requires-Dist: pytest-rerunfailures; extra == 'tests'
Requires-Dist: pytest-tornasync; extra == 'tests'
Requires-Dist: pytest-xdist; extra == 'tests'
Requires-Dist: pytest>=7; extra == 'tests'
Requires-Dist: requests-mock; extra == 'tests'
Requires-Dist: wheel; extra == 'tests'
